movatalk/__init__.py
movatalk/__main__.py
movatalk/_version.py
movatalk/config/__init__.py
movatalk-0.1.44.dist-info/METADATA
movatalk-0.1.44.dist-info/WHEEL
movatalk-0.1.44.dist-info/top_level.txt
movatalk-0.1.44.dist-info/RECORD
