Metadata-Version: 2.4
Name: movatalk
Version: 0.1.44
Summary: libs for cameramonit, ocr, fin-officer, cfo, and other projects
Home-page: https://www.movatalk.com
Author: Tom Sapletta
Author-email: tom@sapletta.com
Maintainer: movatalk developers
Maintainer-email: info@softreck.dev
License: Apache-2.0
Project-URL: Repository, https://github.com/movatalk/python
Project-URL: Changelog, https://github.com/movatalk/python/releases
Project-URL: Wiki, https://github.com/movatalk/python/wiki
Project-URL: Issue Tracker, https://github.com/movatalk/python/issues/new
Keywords: python,movatalk,movatalk,movatalk3,movatalk
Classifier: License :: OSI Approved :: Apache Software License
Classifier: Programming Language :: Python
Classifier: Programming Language :: Python :: 3
Classifier: Programming Language :: Python :: 3.7
Classifier: Programming Language :: Python :: 3.8
Classifier: Programming Language :: Python :: 3.9
Classifier: Programming Language :: Python :: 3.10
Classifier: Programming Language :: Python :: 3.11
Requires-Python: >=3.7
Dynamic: author
Dynamic: author-email
Dynamic: classifier
Dynamic: description
Dynamic: description-content-type
Dynamic: home-page
Dynamic: keywords
Dynamic: license
Dynamic: maintainer
Dynamic: maintainer-email
Dynamic: project-url
Dynamic: requires-python
Dynamic: summary
